notifiedby/__init__.py
notifiedby/emails.py
django_notifiedby-0.1.4.dist-info/LICENSE
django_notifiedby-0.1.4.dist-info/METADATA
django_notifiedby-0.1.4.dist-info/WHEEL
django_notifiedby-0.1.4.dist-info/top_level.txt
django_notifiedby-0.1.4.dist-info/RECORD
