Metadata-Version: 2.2
Name: django-notifiedby
Version: 0.1.4
Summary: Send emails the easy way
License: Copyright 2025 Rezero Consulting Ltd
Requires-Python: >=3.8
License-File: LICENSE
Requires-Dist: django>=3.2
